[
  {
    "title": "Default",
    "data": {
      "type": "ContentBlock",
      "data": {
        "title": "Markdown Support Example",
        "subtitle": "Authoring content with Markdown",
        "format": "markdown",
        "image": {
          "imageSrc": "https://images.unsplash.com/photo-1542831371-29b0f74f9713?ixlib=rb-1.2.1&auto=format&fit=crop&w=1350&q=80",
          "alt": "Code editor",
          "caption": "Writing in Markdown"
        },
        "content": "**SankhyaBook 365** is—and will always be—**free to use**. We believe that world-class knowledge management should be accessible to every organization on Microsoft 365. We sustain our development through optional, high-value professional services for teams that need a tailored touch.\n\n----------\n\n### Choose Your Path\n\n|**Feature**  | **Community Edition (Free)** |**Customization Support (Paid)**\n|--|--|--|\n|**License Cost**  | **$0 / month** | **Contact us**   |\n|**User Limit**|Unlimited|Unlimited|\n| **Core Features** |All Hierarchy & Search tools| All Hierarchy & Search tools\n|**Updates**|Regular Store Updates| Based on agreement |\n| **Deployment** | Self-Service | **Guided Installation & Setup** |\n| **Customization** | Standard Web Part Properties | **Custom CSS & Feature Dev** |\n| **Support** | Community / Documentation | **Direct Priority Email Support** |\n\n----------\n\n## 🛠️ Optional Professional Services\n\n_Need something beyond the box? Our engineering team is available for bespoke engagements._\n\n### 1. Expert Deployment & Onboarding\n\nEnsure your knowledge base is architected correctly from day one. We assist with:\n\n-   Tenant-wide deployment and API permission auditing.\n    \n-   Migration of existing SharePoint Wiki or Page content into SankhyaBook 365 hierarchies.\n    \n-   Training sessions for Site Owners and Content Managers.\n    \n\n### 2. Bespoke Customization\n\nWhile SankhyaBook 365 is feature-rich, your organization may have specific branding or functional requirements.\n\n-   **Custom UI/UX:** Tailored CSS to match your corporate brand identity perfectly.\n    \n-   **Feature Requests:** Need a specific integration? We can develop custom extensions for your tenant.\n    \n-   **Private Builds:** Dedicated versions of the web part for highly regulated environments.\n    \n\n### 3. Managed Support SLA\n\nFor organizations requiring guaranteed response times and technical peace of mind.\n\n-   Dedicated Support Engineer.\n    \n-   24-hour initial response time.\n    \n-   Direct screen-share troubleshooting sessions."
      }
    }
  }
]